odoo8_addon_ngo_purchase-8.0.1.2.0-py2.7-nspkg.pth
odoo_addons/ngo_purchase/__openerp__.py
odoo_addons/ngo_purchase/purchase_order.py
odoo_addons/ngo_purchase/__init__.py
odoo_addons/ngo_purchase/README.rst
odoo_addons/ngo_purchase/view/purchase_order.xml
odoo_addons/ngo_purchase/i18n/ngo_purchase.pot
odoo_addons/ngo_purchase/i18n/en_US.po
odoo_addons/ngo_purchase/model/purchase_order.py
odoo_addons/ngo_purchase/model/__init__.py
odoo8_addon_ngo_purchase-8.0.1.2.0.dist-info/top_level.txt
odoo8_addon_ngo_purchase-8.0.1.2.0.dist-info/WHEEL
odoo8_addon_ngo_purchase-8.0.1.2.0.dist-info/RECORD
odoo8_addon_ngo_purchase-8.0.1.2.0.dist-info/metadata.json
odoo8_addon_ngo_purchase-8.0.1.2.0.dist-info/DESCRIPTION.rst
odoo8_addon_ngo_purchase-8.0.1.2.0.dist-info/METADATA
odoo8_addon_ngo_purchase-8.0.1.2.0.dist-info/namespace_packages.txt
