Metadata-Version: 2.0
Name: odoo8-addon-ngo-purchase
Version: 8.0.1.2.0
Summary: Base Purchase Order view for NGO
Home-page: http://www.camptocamp.com
Author: UNKNOWN
Author-email: UNKNOWN
License: AGPL-3
Platform: UNKNOWN
Requires-Dist: odoo (<9.0a,>=8.0a)
Requires-Dist: odoo8-addon-framework-agreement
Requires-Dist: odoo8-addon-framework-agreement-requisition
Requires-Dist: odoo8-addon-purchase-delivery-address
Requires-Dist: odoo8-addon-purchase-origin-address
Requires-Dist: odoo8-addon-purchase-requisition-bid-selection
Requires-Dist: odoo8-addon-purchase-rfq-bid-workflow
Requires-Dist: odoo8-addon-purchase-transport-document
Classifier: Programming Language :: Python :: 2.7
Classifier: Framework :: Odoo
Classifier: License :: OSI Approved :: GNU Affero General Public License v3
